{
  "ord_1782229548544_ruigl": {
    "id": "ord_1782229548544_ruigl",
    "answers": {
      "recipientType": "husband",
      "recipientName": "rtgrh",
      "genre": "pop",
      "voiceGender": "no-preference",
      "beautifulQualities": "attentioné\n",
      "specialMoments": "il venanit me voir a tous mes match de foot\n",
      "specialMessage": "que je l'aime",
      "songLanguage": "french",
      "email": "yassine.boumahrou@edu.em-lyon.com",
      "phoneCountryCode": "+212",
      "phoneNumber": "654521529"
    },
    "status": "pending",
    "amount": 79,
    "createdAt": "2026-06-23T15:45:48.544Z"
  },
  "ord_1782235582670_uja9b": {
    "id": "ord_1782235582670_uja9b",
    "answers": {
      "recipientType": "myself",
      "recipientName": "Malik",
      "genre": "rnb",
      "voiceGender": "female",
      "beautifulQualities": "Acharnement, travail,  devotion",
      "specialMoments": "reussite de l'entreprise",
      "specialMessage": "rou7 nayek",
      "songLanguage": "darija",
      "selectedOffer": "standard",
      "email": "yassine.boumahrou@edu.em-lyon.com",
      "phoneCountryCode": "+33",
      "phoneNumber": "0664061331"
    },
    "status": "paid",
    "amount": 190,
    "createdAt": "2026-06-23T17:26:22.670Z"
  },
  "ord_1782236241227_8ldd2": {
    "id": "ord_1782236241227_8ldd2",
    "answers": {
      "recipientType": "myself",
      "recipientName": "fgbthnb",
      "genre": "pop",
      "voiceGender": "male",
      "beautifulQualities": "tbtgbtnyntgb",
      "specialMoments": "rgegbrthn",
      "specialMessage": "('th'(h§§y",
      "songLanguage": "french",
      "selectedOffer": "express",
      "email": "yassine.boumahrou@edu.em-lyon.com",
      "phoneCountryCode": "+33",
      "phoneNumber": "0123456789"
    },
    "status": "paid",
    "amount": 290,
    "createdAt": "2026-06-23T17:37:21.227Z"
  },
  "ord_1782236389927_pwqkb": {
    "id": "ord_1782236389927_pwqkb",
    "answers": {
      "recipientType": "children",
      "recipientName": "fevvf",
      "genre": "rock",
      "voiceGender": "male",
      "beautifulQualities": "vfvfv",
      "specialMoments": "fvffvfvvffvfv",
      "specialMessage": "fvfdwbfbdfb",
      "songLanguage": "french",
      "selectedOffer": "express",
      "email": "yassine.boumahrou@edu.em-lyon.com",
      "phoneCountryCode": "+33",
      "phoneNumber": "633289987"
    },
    "status": "pending",
    "amount": 290,
    "createdAt": "2026-06-23T17:39:49.927Z"
  },
  "ord_1782237619616_w0uto": {
    "id": "ord_1782237619616_w0uto",
    "answers": {
      "recipientType": "myself",
      "recipientName": "fvzegzef",
      "genre": "chaabi",
      "customGenre": "",
      "voiceGender": "female",
      "beautifulQualities": "fvzezer",
      "specialMoments": "zefvzefvzefv",
      "specialMessage": "efzefvzefv",
      "songLanguage": "tarifit",
      "selectedOffer": "express",
      "email": "yassine.boumahrou@edu.em-lyon.com",
      "phoneCountryCode": "+33",
      "phoneNumber": "123456789"
    },
    "status": "paid",
    "amount": 290,
    "createdAt": "2026-06-23T18:00:19.616Z"
  },
  "ord_1782239116485_erou7": {
    "id": "ord_1782239116485_erou7",
    "answers": {
      "recipientType": "children",
      "recipientName": "dfvdfvf",
      "genre": "rap-marocain",
      "customGenre": "",
      "voiceGender": "female",
      "beautifulQualities": "dfvvdffvfdv",
      "specialMoments": "vfdvfdfffv",
      "specialMessage": "vfdvfdvffvfdvf",
      "songLanguage": "french",
      "selectedOffer": "express",
      "email": "yas@dfjdk.com",
      "phoneCountryCode": "+33",
      "phoneNumber": "633289986"
    },
    "status": "pending",
    "amount": 290,
    "createdAt": "2026-06-23T18:25:16.485Z"
  },
  "ord_1782239179124_to7ep": {
    "id": "ord_1782239179124_to7ep",
    "answers": {
      "recipientType": "other",
      "recipientName": "dsdfvfdv",
      "genre": "rap-marocain",
      "customGenre": "",
      "voiceGender": "male",
      "beautifulQualities": "dvfvfvfdvf",
      "specialMoments": "vdfvffdfvdvffvd",
      "specialMessage": "dfvvffvdfvd",
      "songLanguage": "french",
      "selectedOffer": "standard",
      "email": "yassine.boumahrou@edu.em-lyon.com",
      "phoneCountryCode": "+33",
      "phoneNumber": "633289986"
    },
    "status": "paid",
    "amount": 190,
    "createdAt": "2026-06-23T18:26:19.124Z"
  },
  "ord_1782244190602_myn65": {
    "id": "ord_1782244190602_myn65",
    "answers": {
      "recipientType": "wife",
      "recipientName": "Yassine",
      "genre": "classique-oriental",
      "customGenre": "",
      "voiceGender": "female",
      "beautifulQualities": "jdjdjfjff",
      "specialMoments": "jfjfkfkflf",
      "specialMessage": "ff,jkekd,d",
      "songLanguage": "french",
      "selectedOffer": "express",
      "email": "yassboum17@gmail.com",
      "phoneCountryCode": "+33",
      "phoneNumber": "633289986"
    },
    "status": "paid",
    "amount": 290,
    "createdAt": "2026-06-23T19:49:50.602Z"
  },
  "ord_1782245255353_e2tcf": {
    "id": "ord_1782245255353_e2tcf",
    "answers": {
      "recipientType": "wife",
      "recipientName": "kjqsdl",
      "genre": "pop-marocaine",
      "customGenre": "",
      "voiceGender": "female",
      "beautifulQualities": "ebjrndfvk",
      "specialMoments": "fin dkfjnvkdlf",
      "specialMessage": "zen ,;dfnel",
      "songLanguage": "french",
      "selectedOffer": "express",
      "email": "yassboum17@gmil.com",
      "phoneCountryCode": "+33",
      "phoneNumber": "633289986"
    },
    "status": "pending",
    "amount": 290,
    "createdAt": "2026-06-23T20:07:35.354Z"
  },
  "ord_1782245834476_vor2h": {
    "id": "ord_1782245834476_vor2h",
    "answers": {
      "recipientType": "wife",
      "recipientName": "Sanae",
      "genre": "gnawa",
      "customGenre": "",
      "voiceGender": "female",
      "beautifulQualities": "qskld,vlkqsdv,n",
      "specialMoments": "fkvndklfnvdkflv",
      "specialMessage": "lkqsd,vdklsfv,dflkv",
      "songLanguage": "french",
      "selectedOffer": "express",
      "email": "yas@iza.com",
      "phoneCountryCode": "+33",
      "phoneNumber": "633289987"
    },
    "status": "paid",
    "amount": 290,
    "createdAt": "2026-06-23T20:17:14.476Z"
  },
  "ord_1782313313386_oxyq9": {
    "id": "ord_1782313313386_oxyq9",
    "answers": {
      "recipientType": "husband",
      "recipientName": "jbjkn",
      "genre": "rai",
      "customGenre": "",
      "voiceGender": "male",
      "beautifulQualities": "kjnknknkl",
      "specialMoments": "jknknlk",
      "specialMessage": "j n:kjn nl;",
      "songLanguage": "french",
      "selectedOffer": "express",
      "email": "yassine.boumahrou@edu.em-lyon.com",
      "phoneCountryCode": "+33",
      "phoneNumber": "633289986"
    },
    "status": "pending",
    "amount": 290,
    "createdAt": "2026-06-24T15:01:53.386Z"
  },
  "ord_1782313450359_gb4kd": {
    "id": "ord_1782313450359_gb4kd",
    "answers": {
      "recipientType": "wife",
      "recipientName": "ihkjnkl=",
      "genre": "chaabi",
      "customGenre": "",
      "voiceGender": "no-preference",
      "beautifulQualities": "kjnk:jn:kn",
      "specialMoments": ":n:nj:k",
      "specialMessage": "nj;,:n:",
      "songLanguage": "french",
      "selectedOffer": "express",
      "email": "yassine.boumahrou@edu.em-lyon.com",
      "phoneCountryCode": "+33",
      "phoneNumber": "63389986"
    },
    "status": "pending",
    "amount": 290,
    "createdAt": "2026-06-24T15:04:10.359Z"
  },
  "ord_1782399702373_d7irn": {
    "id": "ord_1782399702373_d7irn",
    "answers": {
      "recipientType": "father",
      "recipientName": "kljkjkjcx",
      "genre": "rai",
      "customGenre": "",
      "voiceGender": "no-preference",
      "beautifulQualities": "fdfdfdfdf",
      "specialMoments": "fdfdffdfdf",
      "specialMessage": "fdfdfddffdfd",
      "songLanguage": "french",
      "selectedOffer": "express",
      "email": "yassboum17@gmail.com",
      "phoneCountryCode": "+33",
      "phoneNumber": "63389986"
    },
    "status": "pending",
    "amount": 290,
    "createdAt": "2026-06-25T15:01:42.373Z"
  },
  "ord_1782399917311_aqjhi": {
    "id": "ord_1782399917311_aqjhi",
    "answers": {
      "recipientType": "husband",
      "recipientName": "sdvcdv",
      "genre": "rai",
      "customGenre": "",
      "voiceGender": "no-preference",
      "beautifulQualities": "fvvffvfv",
      "specialMoments": "ffvfvvfv",
      "specialMessage": "ffvfvvffv",
      "songLanguage": "french",
      "selectedOffer": "standard",
      "email": "yassine.boumahrou@edu.em-lyon.com",
      "phoneCountryCode": "+33",
      "phoneNumber": "633289986"
    },
    "status": "pending",
    "amount": 190,
    "createdAt": "2026-06-25T15:05:17.311Z"
  },
  "ord_1782401924197_22ooq": {
    "id": "ord_1782401924197_22ooq",
    "answers": {
      "recipientType": "husband",
      "recipientName": "jn,n, ",
      "genre": "rai",
      "customGenre": "",
      "voiceGender": "male",
      "beautifulQualities": "nn,n ;,n",
      "specialMoments": ",n jnknnlkl",
      "specialMessage": "jlllklkl",
      "songLanguage": "french",
      "selectedOffer": "express",
      "email": "yassboum17@gmail.com",
      "phoneCountryCode": "+33",
      "phoneNumber": "633289986"
    },
    "status": "pending",
    "amount": 290,
    "createdAt": "2026-06-25T15:38:44.197Z"
  },
  "ord_1782852802630_my9y2": {
    "id": "ord_1782852802630_my9y2",
    "answers": {
      "recipientType": "other",
      "recipientName": "شنو سميتو؟",
      "genre": "classique-oriental",
      "customGenre": "",
      "voiceGender": "female",
      "beautifulQualities": "أحسن الصفات ديالو\n",
      "specialMoments": "أحسن الصفات ديالو\n",
      "specialMessage": "أحسن الصفات ديالو\n",
      "songLanguage": "french",
      "selectedOffer": "express",
      "email": "Yesss17@gmail.com",
      "phoneCountryCode": "+33",
      "phoneNumber": "633666666"
    },
    "status": "pending",
    "amount": 290,
    "createdAt": "2026-06-30T20:53:22.630Z"
  },
  "ord_1783171663128_bgpwy": {
    "id": "ord_1783171663128_bgpwy",
    "answers": {
      "recipientType": "sibling",
      "recipientName": "Malik",
      "genre": "rap-marocain",
      "customGenre": "",
      "voiceGender": "male",
      "beautifulQualities": "Sincere on peut compter sur lui il a le sens de la famille",
      "specialMoments": "Quand on joue à TFT ou qu'on sortait en boite à Alicante ou dans les coffee shop",
      "specialMessage": "C'est un bon je lui souhaite la santé et la réussite",
      "songLanguage": "french",
      "selectedOffer": "express",
      "email": "yassboum17@gmail.com",
      "phoneCountryCode": "+33",
      "phoneNumber": "633289986"
    },
    "status": "pending",
    "amount": 290,
    "createdAt": "2026-07-04T13:27:43.128Z"
  },
  "ord_1783172101181_d4729": {
    "id": "ord_1783172101181_d4729",
    "answers": {
      "recipientType": "sibling",
      "recipientName": "Malik",
      "genre": "rap-marocain",
      "customGenre": "",
      "voiceGender": "male",
      "beautifulQualities": "C'est un bon",
      "specialMoments": "Quand on sortait en boite à Alicante et au coffee shop",
      "specialMessage": "Santé et réussite",
      "songLanguage": "french",
      "selectedOffer": "express",
      "email": "yassboum17@gmail.com",
      "phoneCountryCode": "+33",
      "phoneNumber": "633289986"
    },
    "status": "pending",
    "amount": 290,
    "createdAt": "2026-07-04T13:35:01.181Z"
  },
  "ord_1783173184858_tmevr": {
    "id": "ord_1783173184858_tmevr",
    "answers": {
      "recipientType": "sibling",
      "recipientName": "Malik",
      "genre": "rap-marocain",
      "customGenre": "",
      "voiceGender": "male",
      "beautifulQualities": "C'zest un bon",
      "specialMoments": "Quand on sort en boite ",
      "specialMessage": "santé et réussite",
      "songLanguage": "french",
      "selectedOffer": "express",
      "email": "yassine.boumahrou@edu.em-lyon.com",
      "phoneCountryCode": "+33",
      "phoneNumber": "666666666"
    },
    "status": "pending",
    "amount": 290,
    "createdAt": "2026-07-04T13:53:04.858Z"
  },
  "ord_1783531337657_ahqb8": {
    "id": "ord_1783531337657_ahqb8",
    "answers": {
      "recipientType": "sibling",
      "recipientName": "omar",
      "genre": "rap-marocain",
      "customGenre": "",
      "voiceGender": "male",
      "beautifulQualities": "Genereux, protecteur, amical et il aime la play 5, surtout 007 le dernier la",
      "specialMoments": "Quand il laissait pas jouer à la player du coup je cachais les manettes",
      "specialMessage": "Je t'aime et froce honneir prince valeur aussi",
      "songLanguage": "french",
      "selectedOffer": "express",
      "email": "yassboum17@gmail.com",
      "phoneCountryCode": "+33",
      "phoneNumber": "633289986"
    },
    "status": "pending",
    "amount": 280,
    "createdAt": "2026-07-08T17:22:17.658Z",
    "previewStatus": "failed",
    "hasListenedToPreview": false
  },
  "ord_1783787683616_rzzpw": {
    "id": "ord_1783787683616_rzzpw",
    "answers": {
      "recipientType": "myself",
      "recipientName": "malik",
      "genre": "chaabi",
      "customGenre": "",
      "voiceGender": "male",
      "beautifulQualities": "rojola",
      "specialMoments": "sbanya alicante valencia",
      "specialMessage": "ta7iati",
      "songLanguage": "french",
      "selectedOffer": "express",
      "email": "toutleplus@gmail.com",
      "phoneCountryCode": "+34",
      "phoneNumber": "664061331"
    },
    "status": "pending",
    "amount": 280,
    "createdAt": "2026-07-11T16:34:43.616Z",
    "previewStatus": "failed",
    "hasListenedToPreview": false
  }
}